insight_eval/__init__.py
insight_eval/batch_scripts/__init__.py
insight_eval/batch_scripts/data/agents_evaluations/agent1/Ex1/combined_score.json
insight_eval/batch_scripts/data/agents_evaluations/agent1/Ex1/coverage.json
insight_eval/batch_scripts/data/agents_evaluations/agent1/Ex1/ground_truth_coverage.json
insight_eval/batch_scripts/data/agents_evaluations/agent1/Ex1/ground_truth_performance.json
insight_eval/batch_scripts/data/agents_evaluations/agent1/Ex1/performance.json
insight_eval/batch_scripts/data/agents_evaluations/agent1/Ex1/problem.json
insight_eval/batch_scripts/data/agents_evaluations/agent1/Ex1/solution_attributes.json
insight_eval/batch_scripts/data/agents_evaluations/agent1/Ex2/combined_score.json
insight_eval/batch_scripts/data/agents_evaluations/agent1/Ex2/coverage.json
insight_eval/batch_scripts/data/agents_evaluations/agent1/Ex2/ground_truth_coverage.json
insight_eval/batch_scripts/data/agents_evaluations/agent1/Ex2/ground_truth_performance.json
insight_eval/batch_scripts/data/agents_evaluations/agent1/Ex2/performance.json
insight_eval/batch_scripts/data/agents_evaluations/agent1/Ex2/problem.json
insight_eval/batch_scripts/data/agents_evaluations/agent1/Ex2/solution_attributes.json
insight_eval/batch_scripts/data/agents_evaluations/agent1/eval_agent1.csv
insight_eval/batch_scripts/data/agents_evaluations/agent2/Ex1/combined_score.json
insight_eval/batch_scripts/data/agents_evaluations/agent2/Ex1/coverage.json
insight_eval/batch_scripts/data/agents_evaluations/agent2/Ex1/ground_truth_coverage.json
insight_eval/batch_scripts/data/agents_evaluations/agent2/Ex1/ground_truth_performance.json
insight_eval/batch_scripts/data/agents_evaluations/agent2/Ex1/performance.json
insight_eval/batch_scripts/data/agents_evaluations/agent2/Ex1/problem.json
insight_eval/batch_scripts/data/agents_evaluations/agent2/Ex1/solution_attributes.json
insight_eval/batch_scripts/data/agents_evaluations/agent2/Ex2/combined_score.json
insight_eval-0.1.1.dist-info/LICENSE
insight_eval-0.1.1.dist-info/METADATA
insight_eval-0.1.1.dist-info/WHEEL
insight_eval-0.1.1.dist-info/RECORD
