Metadata-Version: 2.3
Name: insight_eval
Version: 0.1.1
Summary: Open source repo for the insight-discovery benchmarking evaluation framework
License: Apache-2.0
Author: Sparkbeyond
Author-email: support@sparkbeyond.com
Requires-Python: >=3.12.1,<4.0.0
Classifier: License :: OSI Approved :: Apache Software License
Classifier: Programming Language :: Python :: 3
Classifier: Programming Language :: Python :: 3.13
Requires-Dist: attrs (>=24.1.0,<25.0.0)
Requires-Dist: cattrs (>=24.1.0,<25.0.0)
Requires-Dist: natsort (==8.4.0)
Requires-Dist: numpy (==2.0.1)
Requires-Dist: pandas (==2.2.2)
Requires-Dist: scikit-learn (==1.5.1)
Requires-Dist: scipy (==1.13.0)
Project-URL: Bug Tracker, https://github.com/SparkBeyond/insight-eval/issues
Project-URL: Homepage, https://www.sparkbeyond.ai/
Project-URL: Repository, https://github.com/SparkBeyond/insight-eval
